m4a2text.py
m4a2text-0.1.13.dist-info/METADATA
m4a2text-0.1.13.dist-info/WHEEL
m4a2text-0.1.13.dist-info/entry_points.txt
m4a2text-0.1.13.dist-info/top_level.txt
m4a2text-0.1.13.dist-info/RECORD
